ai_tools_fs/__init__.py
aic_tools_fs-0.0.1.dist-info/LICENSE
aic_tools_fs-0.0.1.dist-info/METADATA
aic_tools_fs-0.0.1.dist-info/WHEEL
aic_tools_fs-0.0.1.dist-info/top_level.txt
aic_tools_fs-0.0.1.dist-info/RECORD
